.coveragerc
.mailmap
.stestr.conf
.travis.yml
AUTHORS
CONTRIBUTING.rst
ChangeLog
HACKING.rst
LICENSE
README.rst
babel.cfg
requirements.txt
setup.cfg
setup.py
test-requirements.txt
tox.ini
.settings/org.eclipse.core.resources.prefs
doc/source/conf.py
doc/source/index.rst
doc/source/readme.rst
doc/source/admin/index.rst
doc/source/cli/index.rst
doc/source/configuration/index.rst
doc/source/contributor/contributing.rst
doc/source/contributor/index.rst
doc/source/install/common_configure.rst
doc/source/install/common_prerequisites.rst
doc/source/install/get_started.rst
doc/source/install/index.rst
doc/source/install/install-obs.rst
doc/source/install/install-rdo.rst
doc/source/install/install-ubuntu.rst
doc/source/install/install.rst
doc/source/install/next-steps.rst
doc/source/install/verify.rst
doc/source/library/index.rst
doc/source/reference/index.rst
doc/source/user/index.rst
etc/vaultlocker.conf
gate/travis-vault.sh
releasenotes/notes/.placeholder
releasenotes/source/conf.py
releasenotes/source/index.rst
releasenotes/source/unreleased.rst
releasenotes/source/_static/.placeholder
releasenotes/source/_templates/.placeholder
tools/vaultlocker-decrypt@.service
vaultlocker/__init__.py
vaultlocker/dmcrypt.py
vaultlocker/shell.py
vaultlocker/systemd.py
vaultlocker.egg-info/PKG-INFO
vaultlocker.egg-info/SOURCES.txt
vaultlocker.egg-info/dependency_links.txt
vaultlocker.egg-info/entry_points.txt
vaultlocker.egg-info/not-zip-safe
vaultlocker.egg-info/pbr.json
vaultlocker.egg-info/requires.txt
vaultlocker.egg-info/top_level.txt
vaultlocker/tests/__init__.py
vaultlocker/tests/functional/__init__.py
vaultlocker/tests/functional/base.py
vaultlocker/tests/functional/test_keystorage.py
vaultlocker/tests/unit/__init__.py
vaultlocker/tests/unit/base.py
vaultlocker/tests/unit/test_dmcrypt.py
vaultlocker/tests/unit/test_systemd.py
vaultlocker/tests/unit/test_vaultlocker.py